cupid/__init__.py
cupid/_version.py
cupid/config.py
cupid/errors.py
cupid/rpc.py
cupid/session.py
cupid/utils.py
cupid/io/__init__.py
cupid/io/kvstore.py
cupid/io/table/__init__.py
cupid/io/table/core.py
cupid/io/table/record.py
cupid/proto/__init__.py
cupid/proto/cupid_process_service_pb2.py
cupid/proto/cupid_subprocess_service_pb2.py
cupid/proto/cupid_task_service_pb2.py
cupid/proto/cupidtaskparam_pb2.py
cupid/proto/kv_store_service_pb2.py
cupid/runtime/__init__.py
cupid/runtime/ctypes_libs.py
cupid/runtime/runtime.py
cupid/runtime/runtime_test.py
odps/__init__.py
odps/_version.py
odps/accounts.py
odps/compat.py
odps/config.py
odps/conftest.py
odps/console.py
odps/core.py
odps/counters.py
odps/crc.py
odps/dag.py
odps/dbapi.py
odps/distcache.py
odps/errors.py
odps/inter.py
odps/readers.py
odps/rest.py
odps/serializers.py
odps/sqlalchemy_odps.py
odps/superset_odps.py
odps/tempobj.py
odps/types.py
odps/utils.py
odps/apis/__init__.py
odps/apis/storage_api/__init__.py
odps/apis/storage_api/conftest.py
odps/apis/storage_api/storage_api.py
odps/df/__init__.py
odps/df/core.py
odps/df/delay.py
odps/df/engines.py
odps/df/examples.py
odps/df/types.py
odps/df/ui.py
odps/df/utils.py
odps/df/backends/__init__.py
odps/df/backends/analyzer.py
odps/df/backends/context.py
odps/df/backends/core.py
odps/df/backends/engine.py
odps/df/backends/errors.py
odps/df/backends/formatter.py
odps/df/backends/frame.py
odps/df/backends/rewriter.py
odps/df/backends/selecter.py
odps/df/backends/utils.py
odps/df/backends/odpssql/__init__.py
odps/df/backends/odpssql/analyzer.py
odps/df/backends/odpssql/codegen.py
odps/df/backends/odpssql/compiler.py
odps/df/backends/odpssql/context.py
odps/df/backends/odpssql/engine.py
odps/df/backends/odpssql/models.py
odps/df/backends/odpssql/rewriter.py
odps/df/backends/odpssql/tunnel.py
odps/df/backends/odpssql/types.py
odps/df/backends/optimize/__init__.py
odps/df/backends/optimize/columnpruning.py
odps/df/backends/optimize/core.py
pyodps-0.12.5.1.dist-info/License
pyodps-0.12.5.1.dist-info/METADATA
pyodps-0.12.5.1.dist-info/WHEEL
pyodps-0.12.5.1.dist-info/entry_points.txt
pyodps-0.12.5.1.dist-info/top_level.txt
pyodps-0.12.5.1.dist-info/RECORD
