Metadata-Version: 2.1
Name: pyodps
Version: 0.12.5.1
Summary: ODPS Python SDK and data analysis framework
Home-page: http://github.com/aliyun/aliyun-odps-python-sdk
Author: Wu Wei
Author-email: weiwu@cacheme.net
Maintainer: Wenjun Si
Maintainer-email: wenjun.swj@alibaba-inc.com
License: Apache License 2.0
Classifier: Operating System :: OS Independent
Classifier: Programming Language :: Python
Classifier: Programming Language :: Python :: 2
Classifier: Programming Language :: Python :: 2.7
Classifier: Programming Language :: Python :: 3
Classifier: Programming Language :: Python :: 3.4
Classifier: Programming Language :: Python :: 3.5
Classifier: Programming Language :: Python :: 3.6
Classifier: Programming Language :: Python :: 3.7
Classifier: Programming Language :: Python :: 3.8
Classifier: Programming Language :: Python :: 3.9
Classifier: Programming Language :: Python :: 3.10
Classifier: Programming Language :: Python :: 3.11
Classifier: Programming Language :: Python :: Implementation :: CPython
Classifier: Programming Language :: Python :: Implementation :: PyPy
Classifier: Topic :: Software Development :: Libraries
Requires-Dist: requests >=2.4.0
Requires-Dist: pyarrow >=0.16.0 ; python_version < "3"
Requires-Dist: pyarrow >=2.0.0 ; python_version >= "3"
Provides-Extra: full
Requires-Dist: jupyter >=1.0.0 ; extra == 'full'
Requires-Dist: ipython >=4.0.0 ; extra == 'full'
Requires-Dist: numpy >=1.6.0 ; extra == 'full'
Requires-Dist: pandas >=0.17.0 ; extra == 'full'
Requires-Dist: matplotlib >=1.4 ; extra == 'full'
Requires-Dist: graphviz >=0.4 ; extra == 'full'
Requires-Dist: greenlet >=0.4.10 ; extra == 'full'
Requires-Dist: ipython <6.0.0 ; (python_version < "3") and extra == 'full'
Requires-Dist: cython >=0.20 ; (sys_platform != "win32") and extra == 'full'
Provides-Extra: mars
Requires-Dist: pymars >=0.5.4 ; extra == 'mars'
Requires-Dist: protobuf <4.0,>=3.6 ; extra == 'mars'
